{
  "ts": "2026-07-23T07:44:08+00:00",
  "price": 65401.93,
  "funding_rate": 1.4e-05,
  "perp_basis_pct": -0.05190978309049456,
  "funding_mean_30d": 3.8844444444444446e-05,
  "oi_btc": 646402056.0,
  "oi_change_24h_pct": -1.702918527173284,
  "top_ls_ratio": 0.5853658536585366,
  "global_ls_ratio": 1.1023764890850818,
  "taker_ratio": 0.8138539069060065,
  "deriv_source": "gate.io(备用)",
  "deribit_index": 65356.42,
  "dvol": 38.36,
  "skew_25d": 1.1300000000000026,
  "atm_iv_near": 36.63,
  "near_expiry_days": 8.0,
  "atm_iv_next": 36.39,
  "term_slope": -0.240000000000002,
  "next_expiry_days": 36.0,
  "flags": {
    "funding_rate": {
      "level": 0,
      "side": null,
      "note": "历史百分位 29%"
    },
    "top_ls_ratio": {
      "level": 1,
      "side": "short",
      "note": "历史百分位 20%"
    },
    "global_ls_ratio": {
      "level": 0,
      "side": null,
      "note": "历史百分位 29%"
    },
    "perp_basis_pct": {
      "level": 1,
      "side": "short",
      "note": "历史百分位 11%"
    },
    "skew_25d": {
      "level": 2,
      "side": "long",
      "note": "历史百分位 3%"
    },
    "dvol": {
      "level": 0,
      "side": null,
      "note": "历史百分位 38%"
    }
  },
  "bias_score": 0
}